sequenceextractions/README.md
sequenceextractions/__init__.py
sequenceextractions/analyzer.py
sequenceextractions-0.1.3.dist-info/METADATA
sequenceextractions-0.1.3.dist-info/WHEEL
sequenceextractions-0.1.3.dist-info/RECORD
